jobcalc/__init__.py
jobcalc/cli.py
jobcalc/config.py
jobcalc/core.py
jobcalc/exceptions.py
jobcalc/formatters.py
jobcalc/param_types.py
jobcalc/utils.py
jobcalc-0.1.1.dist-info/DESCRIPTION.rst
jobcalc-0.1.1.dist-info/METADATA
jobcalc-0.1.1.dist-info/RECORD
jobcalc-0.1.1.dist-info/WHEEL
jobcalc-0.1.1.dist-info/entry_points.txt
jobcalc-0.1.1.dist-info/metadata.json
jobcalc-0.1.1.dist-info/top_level.txt
tests/__init__.py
tests/conftest.py
tests/test_cli.py
tests/test_config.py
tests/test_core.py
tests/test_exceptions.py
tests/test_formatters.py
tests/test_param_types.py
tests/test_utils.py
