Metadata-Version: 2.0
Name: jobcalc
Version: 0.1.1
Summary: Job calculator utilities and command line application.
Home-page: https://github.com/m-housh/jobcalc
Author: Michael Housh
Author-email: mhoush@houshhomeenergy.com
License: MIT license
Keywords: jobcalc
Platform: UNKNOWN
Classifier: Development Status :: 2 - Pre-Alpha
Classifier: Intended Audience :: Developers
Classifier: License :: OSI Approved :: MIT License
Classifier: Natural Language :: English
Classifier: Programming Language :: Python :: 3.5
Requires-Dist: Click (>=6.6)
Requires-Dist: babel (>=2.3.4)
Requires-Dist: colorclass (>=2.2.0)
Requires-Dist: pyyaml (==3.11)
Requires-Dist: terminaltables (>=3.0.0)
Requires-Dist: wrapt (>=1.10.8)
